publish_example/__init__.py
publish_example/main.py
publish_example-1.1.dist-info/METADATA
publish_example-1.1.dist-info/WHEEL
publish_example-1.1.dist-info/top_level.txt
publish_example-1.1.dist-info/RECORD
