Metadata-Version: 2.1
Name: publish-example
Version: 1.1
Summary: A simple example package
Author: handsome victor 666
Author-email: handsomevictor0054@gmail.com
Requires-Dist: numpy
